[
    {
        "id": "20260217165739553433",
        "timestamp": "2026-02-17T16:57:39.553471",
        "type": "Video Check",
        "verdict": "Analyzed",
        "risk": "High",
        "score": 0,
        "details": {
            "video_label": "AI Generated Video",
            "ai_frame_percentage": 90.91,
            "total_frames_analyzed": 11,
            "risk_level": "High",
            "explanation": "Video analysis complete. Processed 11 frames. 90% of frames showed high AI indicators, while 100% showed moderate signs.",
            "average_ai_score": 95.2
        }
    },
    {
        "id": "20260217165725275036",
        "timestamp": "2026-02-17T16:57:25.275093",
        "type": "Video Check",
        "verdict": "Analyzed",
        "risk": "Low",
        "score": 0,
        "details": {
            "video_label": "Likely Real Video",
            "ai_frame_percentage": 10.94,
            "total_frames_analyzed": 64,
            "risk_level": "Low",
            "explanation": "Video analysis complete. Processed 64 frames. 10% of frames showed high AI indicators, while 21% showed moderate signs.",
            "average_ai_score": 22.48
        }
    },
    {
        "id": "20260217165503436094",
        "timestamp": "2026-02-17T16:55:03.436130",
        "type": "Text Check",
        "verdict": "Analyzed",
        "risk": "Medium",
        "score": 51.11,
        "details": {
            "text_score": 51.11,
            "reliable_prob": 48.89,
            "hallucination_prob": 51.11,
            "risk_level": "Medium",
            "explanation": "Moderate signs of linguistic uncertainty or ungrounded claims.",
            "model_status": "Active"
        }
    },
    {
        "id": "20260217165449956597",
        "timestamp": "2026-02-17T16:54:49.956670",
        "type": "Text Check",
        "verdict": "Analyzed",
        "risk": "Low",
        "score": 49.11,
        "details": {
            "text_score": 49.11,
            "reliable_prob": 50.89,
            "hallucination_prob": 49.11,
            "risk_level": "Low",
            "explanation": "Content appears reliable and grounded according to NLP audit.",
            "model_status": "Active"
        }
    },
    {
        "id": "20260217165423669889",
        "timestamp": "2026-02-17T16:54:23.669978",
        "type": "Text Check",
        "verdict": "Analyzed",
        "risk": "Low",
        "score": 49.11,
        "details": {
            "text_score": 49.11,
            "reliable_prob": 50.89,
            "hallucination_prob": 49.11,
            "risk_level": "Low",
            "explanation": "Content appears reliable and grounded according to NLP audit.",
            "model_status": "Active"
        }
    },
    {
        "id": "20260217164209438916",
        "timestamp": "2026-02-17T16:42:09.438948",
        "type": "Text Check",
        "verdict": "Analyzed",
        "risk": "Low",
        "score": 47.63,
        "details": {
            "text_score": 47.63,
            "reliable_prob": 52.37,
            "hallucination_prob": 47.63,
            "risk_level": "Low",
            "explanation": "Content appears reliable and grounded according to NLP audit.",
            "model_status": "Active"
        }
    },
    {
        "id": "20260217164156678119",
        "timestamp": "2026-02-17T16:41:56.678154",
        "type": "Text Check",
        "verdict": "Analyzed",
        "risk": "Low",
        "score": 47.48,
        "details": {
            "text_score": 47.48,
            "reliable_prob": 52.52,
            "hallucination_prob": 47.48,
            "risk_level": "Low",
            "explanation": "Content appears reliable and grounded according to NLP audit.",
            "model_status": "Active"
        }
    },
    {
        "id": "20260217164137908597",
        "timestamp": "2026-02-17T16:41:37.908628",
        "type": "Text Check",
        "verdict": "Analyzed",
        "risk": "Low",
        "score": 46.53,
        "details": {
            "text_score": 46.53,
            "reliable_prob": 53.47,
            "hallucination_prob": 46.53,
            "risk_level": "Low",
            "explanation": "Content appears reliable and grounded according to NLP audit.",
            "model_status": "Active"
        }
    },
    {
        "id": "20260217164052357940",
        "timestamp": "2026-02-17T16:40:52.357992",
        "type": "Image Check",
        "verdict": "Likely Real Image",
        "risk": "Low",
        "score": 18.27,
        "details": {
            "image_type": "Photograph",
            "cnn_score": 8.95,
            "heuristic_score": 40,
            "score": 18.27,
            "risk_level": "Low",
            "result": "Likely Real Image",
            "explanation": "Audit Result: Likely Real Image based on CNN confidence (8.95%) and structural heuristics (40%). ",
            "metrics": {
                "laplacian_var": 103.55,
                "fft_mean": 179.86,
                "has_exif": true,
                "resolution": "3024x4032"
            }
        }
    },
    {
        "id": "20260217164035062797",
        "timestamp": "2026-02-17T16:40:35.062874",
        "type": "Image Check",
        "verdict": "Likely Real Image",
        "risk": "Low",
        "score": 8.96,
        "details": {
            "image_type": "Photograph",
            "cnn_score": 12.8,
            "heuristic_score": 0,
            "score": 8.96,
            "risk_level": "Low",
            "result": "Likely Real Image",
            "explanation": "Audit Result: Likely Real Image based on CNN confidence (12.8%) and structural heuristics (0%). ",
            "metrics": {
                "laplacian_var": 326.26,
                "fft_mean": 152.44,
                "has_exif": true,
                "resolution": "612x408"
            }
        }
    },
    {
        "id": "20260217164020550525",
        "timestamp": "2026-02-17T16:40:20.550634",
        "type": "Image Check",
        "verdict": "Suspicious Image (Possible AI)",
        "risk": "Medium",
        "score": 55.0,
        "details": {
            "image_type": "Photograph",
            "cnn_score": 9.94,
            "heuristic_score": 35,
            "score": 55.0,
            "risk_level": "Medium",
            "result": "Suspicious Image (Possible AI)",
            "explanation": "Audit Result: Suspicious Image (Possible AI) based on CNN confidence (9.94%) and structural heuristics (35%). Uncertainty markers detected.",
            "metrics": {
                "laplacian_var": 454.64,
                "fft_mean": 167.02,
                "has_exif": false,
                "resolution": "1024x1024"
            }
        }
    },
    {
        "id": "20260217163824288183",
        "timestamp": "2026-02-17T16:38:24.288220",
        "type": "Text Check",
        "verdict": "Analyzed",
        "risk": "Medium",
        "score": 50.66,
        "details": {
            "text_score": 50.66,
            "reliable_prob": 49.34,
            "hallucination_prob": 50.66,
            "risk_level": "Medium",
            "explanation": "Moderate signs of linguistic uncertainty or ungrounded claims.",
            "model_status": "Active"
        }
    },
    {
        "id": "20260217163810737188",
        "timestamp": "2026-02-17T16:38:10.737221",
        "type": "Text Check",
        "verdict": "Analyzed",
        "risk": "Medium",
        "score": 52.83,
        "details": {
            "text_score": 52.83,
            "reliable_prob": 47.17,
            "hallucination_prob": 52.83,
            "risk_level": "Medium",
            "explanation": "Moderate signs of linguistic uncertainty or ungrounded claims.",
            "model_status": "Active"
        }
    },
    {
        "id": "20260217163751300723",
        "timestamp": "2026-02-17T16:37:51.300924",
        "type": "Text Check",
        "verdict": "Analyzed",
        "risk": "Medium",
        "score": 51.53,
        "details": {
            "text_score": 51.53,
            "reliable_prob": 48.47,
            "hallucination_prob": 51.53,
            "risk_level": "Medium",
            "explanation": "Moderate signs of linguistic uncertainty or ungrounded claims.",
            "model_status": "Active"
        }
    },
    {
        "id": "20260217161321889304",
        "timestamp": "2026-02-17T16:13:21.889331",
        "type": "Text Check",
        "verdict": "Analyzed",
        "risk": "Low",
        "score": 47.3,
        "details": {
            "text_score": 47.3,
            "reliable_prob": 52.7,
            "hallucination_prob": 47.3,
            "risk_level": "Low",
            "explanation": "Text appears grounded and reliable based on NLP classification.",
            "model_status": "Active"
        }
    },
    {
        "id": "20260217161138700941",
        "timestamp": "2026-02-17T16:11:38.700968",
        "type": "Text Check",
        "verdict": "Analyzed",
        "risk": "Low",
        "score": 46.0,
        "details": {
            "text_score": 46.0,
            "reliable_prob": 54.0,
            "hallucination_prob": 46.0,
            "risk_level": "Low",
            "explanation": "Text appears grounded and reliable based on NLP classification.",
            "model_status": "Active"
        }
    },
    {
        "id": "20260217161111810641",
        "timestamp": "2026-02-17T16:11:11.810668",
        "type": "Text Check",
        "verdict": "Analyzed",
        "risk": "Low",
        "score": 47.92,
        "details": {
            "text_score": 47.92,
            "reliable_prob": 52.08,
            "hallucination_prob": 47.92,
            "risk_level": "Low",
            "explanation": "Text appears grounded and reliable based on NLP classification.",
            "model_status": "Active"
        }
    },
    {
        "id": "20260217161026176357",
        "timestamp": "2026-02-17T16:10:26.176388",
        "type": "Text Check",
        "verdict": "Analyzed",
        "risk": "Low",
        "score": 45.15,
        "details": {
            "text_score": 45.15,
            "reliable_prob": 54.85,
            "hallucination_prob": 45.15,
            "risk_level": "Low",
            "explanation": "Text appears grounded and reliable based on NLP classification.",
            "model_status": "Active"
        }
    },
    {
        "id": "20260217160730746735",
        "timestamp": "2026-02-17T16:07:30.746779",
        "type": "Text Check",
        "verdict": "Analyzed",
        "risk": "Low",
        "score": 45.15,
        "details": {
            "text_score": 45.15,
            "reliable_prob": 54.85,
            "hallucination_prob": 45.15,
            "risk_level": "Low",
            "explanation": "Text appears grounded and reliable based on NLP classification.",
            "model_status": "Active"
        }
    },
    {
        "id": "20260217160518998988",
        "timestamp": "2026-02-17T16:05:18.999081",
        "type": "Text Check",
        "verdict": "Analyzed",
        "risk": "Low",
        "score": 45.48,
        "details": {
            "text_score": 45.48,
            "reliable_prob": 54.52,
            "hallucination_prob": 45.48,
            "risk_level": "Low",
            "explanation": "Text appears grounded and reliable based on NLP classification.",
            "model_status": "Active"
        }
    },
    {
        "id": "20260217153840146366",
        "timestamp": "2026-02-17T15:38:40.146503",
        "type": "Text Check",
        "verdict": "Analyzed",
        "risk": "Low",
        "score": 15,
        "details": {
            "text_score": 15,
            "risk_level": "Low",
            "explanation": "Missing necessary uncertainty or hedging markers.",
            "detected_signals": [
                "Lack of hedging"
            ]
        }
    },
    {
        "id": "20260217153818995770",
        "timestamp": "2026-02-17T15:38:18.995841",
        "type": "Text Check",
        "verdict": "Analyzed",
        "risk": "Low",
        "score": 15,
        "details": {
            "text_score": 15,
            "risk_level": "Low",
            "explanation": "Missing necessary uncertainty or hedging markers.",
            "detected_signals": [
                "Lack of hedging"
            ]
        }
    },
    {
        "id": "20260217153756055227",
        "timestamp": "2026-02-17T15:37:56.055314",
        "type": "Text Check",
        "verdict": "Analyzed",
        "risk": "Low",
        "score": 0,
        "details": {
            "text_score": 0,
            "risk_level": "Low",
            "explanation": "Text is balanced and moderate.",
            "detected_signals": []
        }
    },
    {
        "id": "20260217150025120579",
        "timestamp": "2026-02-17T15:00:25.120851",
        "type": "Video Check",
        "verdict": "Analyzed",
        "risk": "Low",
        "score": 0,
        "details": {
            "video_label": "Likely Real Video",
            "ai_frame_percentage": 7.0,
            "total_frames_analyzed": 100,
            "risk_level": "Low",
            "explanation": "Video analysis complete. Processed 100 frames. 7% of frames showed high AI indicators, while 21% showed moderate signs.",
            "average_ai_score": 25.26
        }
    },
    {
        "id": "20260217145330793686",
        "timestamp": "2026-02-17T14:53:30.793754",
        "type": "Video Check",
        "verdict": "Analyzed",
        "risk": "High",
        "score": 0,
        "details": {
            "video_label": "AI Generated Video",
            "ai_frame_percentage": 90.91,
            "total_frames_analyzed": 11,
            "risk_level": "High",
            "explanation": "Video analysis complete. Processed 11 frames. 90% of frames showed high AI indicators, while 100% showed moderate signs.",
            "average_ai_score": 95.2
        }
    },
    {
        "id": "20260217145049219876",
        "timestamp": "2026-02-17T14:50:49.219944",
        "type": "Video Check",
        "verdict": "Analyzed",
        "risk": "Low",
        "score": 0,
        "details": {
            "video_label": "Likely Real Video",
            "ai_frame_percentage": 0.0,
            "total_frames_analyzed": 12,
            "risk_level": "Low",
            "explanation": "Video analysis complete. Processed 12 frames. 0% of frames showed high AI indicators, while 0% showed moderate signs.",
            "average_ai_score": 0.89
        }
    },
    {
        "id": "20260217144917574958",
        "timestamp": "2026-02-17T14:49:17.575065",
        "type": "Video Check",
        "verdict": "Analyzed",
        "risk": "Low",
        "score": 0,
        "details": {
            "video_label": "Likely Real Video",
            "ai_frame_percentage": 10.94,
            "total_frames_analyzed": 64,
            "risk_level": "Low",
            "explanation": "Video analysis complete. Processed 64 frames. 10% of frames showed high AI indicators, while 21% showed moderate signs.",
            "average_ai_score": 22.48
        }
    },
    {
        "id": "20260217144832902148",
        "timestamp": "2026-02-17T14:48:32.902237",
        "type": "Video Check",
        "verdict": "Analyzed",
        "risk": "High",
        "score": 0,
        "details": {
            "video_label": "AI Generated Video",
            "ai_frame_percentage": 100.0,
            "total_frames_analyzed": 9,
            "risk_level": "High",
            "explanation": "Video analysis complete. Processed 9 frames. 100% of frames showed high AI indicators, while 100% showed moderate signs.",
            "average_ai_score": 99.99
        }
    },
    {
        "id": "20260217144312139374",
        "timestamp": "2026-02-17T14:43:12.139448",
        "type": "Video Check",
        "verdict": "Analyzed",
        "risk": "High",
        "score": 0,
        "details": {
            "video_label": "AI Generated Video",
            "ai_frame_percentage": 100.0,
            "total_frames_analyzed": 9,
            "risk_level": "High",
            "explanation": "Video analysis complete. Processed 9 frames. 100% of frames showed high AI indicators, while 100% showed moderate signs.",
            "average_ai_score": 99.99
        }
    },
    {
        "id": "20260217142229309358",
        "timestamp": "2026-02-17T14:22:29.309488",
        "type": "Video Check",
        "verdict": "Analyzed",
        "risk": "Low",
        "score": 0,
        "details": {
            "video_label": "Likely Real Video",
            "ai_frame_percentage": 10.94,
            "total_frames_analyzed": 64,
            "risk_level": "Low",
            "explanation": "Video analysis complete. Processed 64 frames. 10% of frames showed high AI indicators, while 21% showed moderate signs.",
            "average_ai_score": 22.48
        }
    },
    {
        "id": "20260217121401896769",
        "timestamp": "2026-02-17T12:14:01.896769",
        "type": "Image Check",
        "verdict": "Suspicious Image (Possible AI)",
        "risk": "Medium",
        "score": 79.93,
        "details": {
            "image_type": "Photograph",
            "cnn_score": 99.18,
            "heuristic_score": 35,
            "score": 79.93,
            "risk_level": "Medium",
            "result": "Suspicious Image (Possible AI)",
            "explanation": "Audit Result: Suspicious Image (Possible AI) based on CNN confidence (99.18%) and structural heuristics (35%). Uncertainty markers detected.",
            "metrics": {
                "laplacian_var": 456.87,
                "fft_mean": 153.48,
                "has_exif": false,
                "resolution": "540x360"
            }
        }
    },
    {
        "id": "20260217121340088905",
        "timestamp": "2026-02-17T12:13:40.088905",
        "type": "Image Check",
        "verdict": "Suspicious Image (Possible AI)",
        "risk": "Medium",
        "score": 77.84,
        "details": {
            "image_type": "Photograph",
            "cnn_score": 85.49,
            "heuristic_score": 60,
            "score": 77.84,
            "risk_level": "Medium",
            "result": "Suspicious Image (Possible AI)",
            "explanation": "Audit Result: Suspicious Image (Possible AI) based on CNN confidence (85.49%) and structural heuristics (60%). Uncertainty markers detected.",
            "metrics": {
                "laplacian_var": 1656.99,
                "fft_mean": 169.22,
                "has_exif": false,
                "resolution": "472x612"
            }
        }
    },
    {
        "id": "20260217121322947920",
        "timestamp": "2026-02-17T12:13:22.947920",
        "type": "Image Check",
        "verdict": "AI Generated Image",
        "risk": "High",
        "score": 92.06,
        "details": {
            "image_type": "Photograph",
            "cnn_score": 99.37,
            "heuristic_score": 75,
            "score": 92.06,
            "risk_level": "High",
            "result": "AI Generated Image",
            "explanation": "Audit Result: AI Generated Image based on CNN confidence (99.37%) and structural heuristics (75%). ",
            "metrics": {
                "laplacian_var": 46.87,
                "fft_mean": 146.1,
                "has_exif": false,
                "resolution": "961x1280"
            }
        }
    },
    {
        "id": "20260217121311698647",
        "timestamp": "2026-02-17T12:13:11.698647",
        "type": "Image Check",
        "verdict": "Likely Real Image",
        "risk": "Low",
        "score": 31.32,
        "details": {
            "image_type": "Photograph",
            "cnn_score": 29.74,
            "heuristic_score": 35,
            "score": 31.32,
            "risk_level": "Low",
            "result": "Likely Real Image",
            "explanation": "Audit Result: Likely Real Image based on CNN confidence (29.74%) and structural heuristics (35%). ",
            "metrics": {
                "laplacian_var": 676.86,
                "fft_mean": 143.86,
                "has_exif": false,
                "resolution": "275x183"
            }
        }
    },
    {
        "id": "20260217121257513674",
        "timestamp": "2026-02-17T12:12:57.513674",
        "type": "Image Check",
        "verdict": "Suspicious Image (Possible AI)",
        "risk": "Medium",
        "score": 76.62,
        "details": {
            "image_type": "Photograph",
            "cnn_score": 77.31,
            "heuristic_score": 75,
            "score": 76.62,
            "risk_level": "Medium",
            "result": "Suspicious Image (Possible AI)",
            "explanation": "Audit Result: Suspicious Image (Possible AI) based on CNN confidence (77.31%) and structural heuristics (75%). Uncertainty markers detected.",
            "metrics": {
                "laplacian_var": 128.9,
                "fft_mean": 156.33,
                "has_exif": false,
                "resolution": "853x1280"
            }
        }
    },
    {
        "id": "20260217121243973647",
        "timestamp": "2026-02-17T12:12:43.973647",
        "type": "Image Check",
        "verdict": "Likely Real Image",
        "risk": "Low",
        "score": 0.01,
        "details": {
            "image_type": "Photograph",
            "cnn_score": 0.01,
            "heuristic_score": 0,
            "score": 0.01,
            "risk_level": "Low",
            "result": "Likely Real Image",
            "explanation": "Audit Result: Likely Real Image based on CNN confidence (0.01%) and structural heuristics (0%). ",
            "metrics": {
                "laplacian_var": 309.61,
                "fft_mean": 129.0,
                "has_exif": true,
                "resolution": "352x481"
            }
        }
    },
    {
        "id": "20260217121228347830",
        "timestamp": "2026-02-17T12:12:28.347830",
        "type": "Image Check",
        "verdict": "Likely Real Image",
        "risk": "Low",
        "score": 18.19,
        "details": {
            "image_type": "Photograph",
            "cnn_score": 0.27,
            "heuristic_score": 60,
            "score": 18.19,
            "risk_level": "Low",
            "result": "Likely Real Image",
            "explanation": "Audit Result: Likely Real Image based on CNN confidence (0.27%) and structural heuristics (60%). ",
            "metrics": {
                "laplacian_var": 3722.17,
                "fft_mean": 147.52,
                "has_exif": false,
                "resolution": "115x108"
            }
        }
    },
    {
        "id": "20260217121218567977",
        "timestamp": "2026-02-17T12:12:18.567977",
        "type": "Image Check",
        "verdict": "AI Generated Image",
        "risk": "High",
        "score": 80.33,
        "details": {
            "image_type": "Photograph",
            "cnn_score": 99.76,
            "heuristic_score": 35,
            "score": 80.33,
            "risk_level": "High",
            "result": "AI Generated Image",
            "explanation": "Audit Result: AI Generated Image based on CNN confidence (99.76%) and structural heuristics (35%). ",
            "metrics": {
                "laplacian_var": 980.96,
                "fft_mean": 176.86,
                "has_exif": false,
                "resolution": "1024x1024"
            }
        }
    },
    {
        "id": "20260217121205505418",
        "timestamp": "2026-02-17T12:12:05.505418",
        "type": "Image Check",
        "verdict": "Suspicious Image (Possible AI)",
        "risk": "Medium",
        "score": 55.0,
        "details": {
            "image_type": "Photograph",
            "cnn_score": 8.9,
            "heuristic_score": 75,
            "score": 55.0,
            "risk_level": "Medium",
            "result": "Suspicious Image (Possible AI)",
            "explanation": "Audit Result: Suspicious Image (Possible AI) based on CNN confidence (8.9%) and structural heuristics (75%). Uncertainty markers detected.",
            "metrics": {
                "laplacian_var": 65.0,
                "fft_mean": 150.86,
                "has_exif": false,
                "resolution": "896x1152"
            }
        }
    },
    {
        "id": "20260217121156457251",
        "timestamp": "2026-02-17T12:11:56.457251",
        "type": "Image Check",
        "verdict": "Likely Real Image",
        "risk": "Low",
        "score": 8.96,
        "details": {
            "image_type": "Photograph",
            "cnn_score": 12.8,
            "heuristic_score": 0,
            "score": 8.96,
            "risk_level": "Low",
            "result": "Likely Real Image",
            "explanation": "Audit Result: Likely Real Image based on CNN confidence (12.8%) and structural heuristics (0%). ",
            "metrics": {
                "laplacian_var": 326.26,
                "fft_mean": 152.44,
                "has_exif": true,
                "resolution": "612x408"
            }
        }
    },
    {
        "id": "20260217121146220934",
        "timestamp": "2026-02-17T12:11:46.220934",
        "type": "Image Check",
        "verdict": "Likely Real Image",
        "risk": "Low",
        "score": 33.84,
        "details": {
            "image_type": "Photograph",
            "cnn_score": 48.34,
            "heuristic_score": 0,
            "score": 33.84,
            "risk_level": "Low",
            "result": "Likely Real Image",
            "explanation": "Audit Result: Likely Real Image based on CNN confidence (48.34%) and structural heuristics (0%). ",
            "metrics": {
                "laplacian_var": 699.33,
                "fft_mean": 170.58,
                "has_exif": true,
                "resolution": "1280x720"
            }
        }
    },
    {
        "id": "20260217121135537049",
        "timestamp": "2026-02-17T12:11:35.537049",
        "type": "Image Check",
        "verdict": "Likely Real Image",
        "risk": "Low",
        "score": 23.39,
        "details": {
            "image_type": "Photograph",
            "cnn_score": 18.41,
            "heuristic_score": 35,
            "score": 23.39,
            "risk_level": "Low",
            "result": "Likely Real Image",
            "explanation": "Audit Result: Likely Real Image based on CNN confidence (18.41%) and structural heuristics (35%). ",
            "metrics": {
                "laplacian_var": 1020.12,
                "fft_mean": 164.89,
                "has_exif": false,
                "resolution": "800x480"
            }
        }
    },
    {
        "id": "20260217121124359889",
        "timestamp": "2026-02-17T12:11:24.359889",
        "type": "Image Check",
        "verdict": "AI Generated Image",
        "risk": "High",
        "score": 80.33,
        "details": {
            "image_type": "Photograph",
            "cnn_score": 99.76,
            "heuristic_score": 35,
            "score": 80.33,
            "risk_level": "High",
            "result": "AI Generated Image",
            "explanation": "Audit Result: AI Generated Image based on CNN confidence (99.76%) and structural heuristics (35%). ",
            "metrics": {
                "laplacian_var": 980.96,
                "fft_mean": 176.86,
                "has_exif": false,
                "resolution": "1024x1024"
            }
        }
    },
    {
        "id": "20260217120215330257",
        "timestamp": "2026-02-17T12:02:15.330904",
        "type": "Image Check",
        "verdict": "Likely Real Image",
        "risk": "Low",
        "score": 12.03,
        "details": {
            "image_type": "Photograph",
            "cnn_score": 0.04,
            "heuristic_score": 40,
            "score": 12.03,
            "risk_level": "Low",
            "result": "Likely Real Image",
            "explanation": "Audit Result: Likely Real Image based on CNN confidence (0.04%) and structural heuristics (40%). ",
            "metrics": {
                "laplacian_var": 61.05,
                "fft_mean": 172.83,
                "has_exif": true,
                "resolution": "3024x4032"
            }
        }
    },
    {
        "id": "20260217120156390396",
        "timestamp": "2026-02-17T12:01:56.391418",
        "type": "Image Check",
        "verdict": "AI Generated Image",
        "risk": "High",
        "score": 80.47,
        "details": {
            "image_type": "Photograph",
            "cnn_score": 99.95,
            "heuristic_score": 35,
            "score": 80.47,
            "risk_level": "High",
            "result": "AI Generated Image",
            "explanation": "Audit Result: AI Generated Image based on CNN confidence (99.95%) and structural heuristics (35%). ",
            "metrics": {
                "laplacian_var": 378.33,
                "fft_mean": 166.17,
                "has_exif": false,
                "resolution": "1024x1024"
            }
        }
    },
    {
        "id": "20260217120139717886",
        "timestamp": "2026-02-17T12:01:39.717886",
        "type": "Image Check",
        "verdict": "AI Generated Image",
        "risk": "High",
        "score": 80.2,
        "details": {
            "image_type": "Photograph",
            "cnn_score": 99.57,
            "heuristic_score": 35,
            "score": 80.2,
            "risk_level": "High",
            "result": "AI Generated Image",
            "explanation": "Audit Result: AI Generated Image based on CNN confidence (99.57%) and structural heuristics (35%). ",
            "metrics": {
                "laplacian_var": 167.61,
                "fft_mean": 172.85,
                "has_exif": false,
                "resolution": "2560x1435"
            }
        }
    },
    {
        "id": "20260217120121245886",
        "timestamp": "2026-02-17T12:01:21.245886",
        "type": "Image Check",
        "verdict": "Other (Graphic/Illustration)",
        "risk": "Low",
        "score": 0,
        "details": {
            "image_type": "Other Image",
            "score": 0,
            "risk_level": "Low",
            "result": "Other (Graphic/Illustration)",
            "explanation": "Detected as a Graphic/Cartoon/Screenshot. Non-photographic images are not subject to Deepfake analysis.",
            "metrics": {
                "is_photo": false
            }
        }
    },
    {
        "id": "20260207135707490982",
        "timestamp": "2026-02-07T13:57:07.491016",
        "type": "Multimodal Firewall",
        "verdict": "WARNING",
        "risk": "Medium",
        "score": 55.0,
        "details": {
            "text_analysis": {
                "text_score": 15,
                "risk_level": "Low",
                "explanation": "Missing necessary uncertainty or hedging markers.",
                "detected_signals": [
                    "Lack of hedging"
                ]
            },
            "image_analysis": {
                "image_type": "Photograph",
                "cnn_score": 5.77,
                "heuristic_score": 35,
                "score": 55.0,
                "risk_level": "Medium",
                "result": "Suspicious Image (Possible AI)",
                "explanation": "Audit Result: Suspicious Image (Possible AI) based on CNN confidence (5.77%) and structural heuristics (35%). Uncertainty markers detected.",
                "metrics": {
                    "laplacian_var": 1143.0,
                    "fft_mean": 198.14,
                    "has_exif": false,
                    "resolution": "1440x5835"
                }
            },
            "firewall_verdict": {
                "verdict": "WARNING",
                "risk_level": "Medium",
                "score": 55.0,
                "decision": "Potential inconsistencies detected. Recommend human verification."
            }
        }
    },
    {
        "id": "20260207135607853252",
        "timestamp": "2026-02-07T13:56:07.853295",
        "type": "Multimodal Firewall",
        "verdict": "SAFE",
        "risk": "Low",
        "score": 22.02,
        "details": {
            "text_analysis": {
                "text_score": 15,
                "risk_level": "Low",
                "explanation": "Missing necessary uncertainty or hedging markers.",
                "detected_signals": [
                    "Lack of hedging"
                ]
            },
            "image_analysis": {
                "image_type": "Photograph",
                "cnn_score": 5.75,
                "heuristic_score": 60,
                "score": 22.02,
                "risk_level": "Low",
                "result": "Likely Real Image",
                "explanation": "Audit Result: Likely Real Image based on CNN confidence (5.75%) and structural heuristics (60%). ",
                "metrics": {
                    "laplacian_var": 3004.37,
                    "fft_mean": 158.32,
                    "has_exif": false,
                    "resolution": "253x291"
                }
            },
            "firewall_verdict": {
                "verdict": "SAFE",
                "risk_level": "Low",
                "score": 22.02,
                "decision": "Content passed security heuristics with low hallucination risk."
            }
        }
    },
    {
        "id": "20260207135510145878",
        "timestamp": "2026-02-07T13:55:10.145940",
        "type": "Text Check",
        "verdict": "Analyzed",
        "risk": "Low",
        "score": 15,
        "details": {
            "text_score": 15,
            "risk_level": "Low",
            "explanation": "Missing necessary uncertainty or hedging markers.",
            "detected_signals": [
                "Lack of hedging"
            ]
        }
    }
]